medinsight/__init__.py
medinsight/agent.py
medinsight/pub_med.py
medinsight-0.0.6.dist-info/LICENSE
medinsight-0.0.6.dist-info/METADATA
medinsight-0.0.6.dist-info/WHEEL
medinsight-0.0.6.dist-info/RECORD
