Metadata-Version: 2.1
Name: medinsight
Version: 0.0.6
Summary: MedInsight - Swarms - 
Home-page: https://github.com/The-Swarm-Corporation/MedInsight-Pro
License: MIT
Keywords: artificial intelligence,deep learning,optimizers,Prompt Engineering
Author: Kye Gomez
Author-email: kye@apac.ai
Requires-Python: >=3.12,<4.0
Classifier: Development Status :: 4 - Beta
Classifier: Intended Audience :: Developers
Classifier: License :: OSI Approved :: MIT License
Classifier: Programming Language :: Python :: 3
Classifier: Programming Language :: Python :: 3.12
Classifier: Programming Language :: Python :: 3.9
Classifier: Topic :: Scientific/Engineering :: Artificial Intelligence
Requires-Dist: biopython
Requires-Dist: loguru
Requires-Dist: pydantic
Requires-Dist: swarms
Project-URL: Documentation, https://github.com/The-Swarm-Corporation/MedInsight-Pro
Project-URL: Repository, https://github.com/The-Swarm-Corporation/MedInsight-Pro
